<?xml version="1.0" encoding="utf-8" ?>
<dwsync>
<file name="index.php" server="C:/AppServ/www/" local="129660622818593750" remote="129660622810000000" />
<file name="modelo.php" server="C:/AppServ/www/" local="129668080433125000" remote="129668080430000000" />
<file name="entregar_donate.php" server="C:/AppServ/www/" local="129662661696718750" remote="129662661690000000" />
<file name="users_online.php" server="C:/AppServ/www/" local="129662318043593750" remote="129662318040000000" />
<file name="cadastrar_novo.php" server="C:/AppServ/www/" local="129662144465000000" remote="129662144460000000" />
<file name="teste.php" server="C:/AppServ/www/" local="129662225701562500" remote="129662225700000000" />
<file name="mural.php" server="C:/AppServ/www/" local="129663569894375000" remote="129663569890000000" />
<file name="user_list.php" server="C:/AppServ/www/" local="129668744647031250" remote="129668744640000000" />
</dwsync>